<?xml version="1.0" encoding="UTF-8"?>
<beans xmlns="http://www.springframework.org/schema/beans"
       xmlns:xsi="http://www.w3.org/2001/XMLSchema-instance"
       xsi:schemaLocation="
        http://www.springframework.org/schema/beans http://www.springframework.org/schema/beans/spring-beans.xsd">

    <!-- bean definitions here -->

    <bean  id="alien" class="org.example.Alien">

       <property name="age" value="21">
<!--           changing the age value using the spring frame work-->

       </property>

    </bean>

<!--    this will make the object of the Alien class 2 times -->
    <bean  id="alien2" class="org.example.Alien">
        <property name="age" value="25" />
    </bean>
    <bean  id="laptop" class="org.example.laptop">



    </bean>
</beans>